trenchrun/__init__.py
trenchrun/__main__.py
trenchrun/argparser.py
trenchrun/blend.py
trenchrun/data.py
trenchrun/do.py
trenchrun/logs.py
trenchrun/main.py
trenchrun/rls.py
trenchrun-0.2.4.dist-info/LICENSE.txt
trenchrun-0.2.4.dist-info/METADATA
trenchrun-0.2.4.dist-info/WHEEL
trenchrun-0.2.4.dist-info/entry_points.txt
trenchrun-0.2.4.dist-info/top_level.txt
trenchrun-0.2.4.dist-info/RECORD
